c8ydp/__init__.py
c8ydp/device_proxy.py
c8y_device_proxy-1.1.1.dist-info/LICENSE
c8y_device_proxy-1.1.1.dist-info/METADATA
c8y_device_proxy-1.1.1.dist-info/WHEEL
c8y_device_proxy-1.1.1.dist-info/top_level.txt
c8y_device_proxy-1.1.1.dist-info/RECORD
