Metadata-Version: 2.1
Name: c8y-device-proxy
Version: 1.1.1
Summary: Cumulocity Device Proxy
Home-page: UNKNOWN
Author: Stefan Witschel
License: Apache v2
Platform: UNKNOWN
License-File: LICENSE
Requires-Dist: paho-mqtt (>=1.5.1)
Requires-Dist: certifi (>=2021.5.30)
Requires-Dist: websocket-client (>=1.2.1)
